tensorflowonspark/TFCluster.py
tensorflowonspark/TFManager.py
tensorflowonspark/TFNode.py
tensorflowonspark/TFParallel.py
tensorflowonspark/TFSparkNode.py
tensorflowonspark/__init__.py
tensorflowonspark/compat.py
tensorflowonspark/dfutil.py
tensorflowonspark/gpu_info.py
tensorflowonspark/marker.py
tensorflowonspark/pipeline.py
tensorflowonspark/reservation.py
tensorflowonspark/util.py
tensorflowonspark-2.2.5.dist-info/LICENSE
tensorflowonspark-2.2.5.dist-info/METADATA
tensorflowonspark-2.2.5.dist-info/WHEEL
tensorflowonspark-2.2.5.dist-info/top_level.txt
tensorflowonspark-2.2.5.dist-info/zip-safe
tensorflowonspark-2.2.5.dist-info/RECORD
