Metadata-Version: 2.1
Name: tensorflowonspark
Version: 2.2.5
Summary: Deep learning with TensorFlow on Apache Spark clusters
Home-page: https://github.com/yahoo/TensorFlowOnSpark
Author: Lee Yang
Author-email: leewyang@gmail.com
License: Apache 2.0
Platform: UNKNOWN
Classifier: Intended Audience :: Developers
Classifier: Intended Audience :: Science/Research
Classifier: License :: OSI Approved :: Apache Software License
Classifier: Topic :: Software Development :: Libraries
Classifier: Programming Language :: Python :: 3 :: Only
Classifier: Programming Language :: Python :: 3.7
Classifier: Programming Language :: Python :: 3.8
Classifier: Programming Language :: Python :: 3.9
Requires-Python: >="3.6"
License-File: LICENSE
Requires-Dist: packaging
Requires-Dist: setuptools (>38.0)
